{"blte7e24e3f9396bf50":{"title":"Header","url":"#","logo":{"image":{"uid":"bltdfe97b157a21772f","created_at":"2020-10-23T07:53:17.583Z","updated_at":"2020-10-23T07:53:17.583Z","created_by":"blt624de4139bf66f89","updated_by":"blt624de4139bf66f89","content_type":"image/png","file_size":"1860","tags":[],"filename":"logo-hover.png","url":"https://images.contentstack.io/v3/assets/blt6b58afa807874c22/bltdfe97b157a21772f/5f928beded5ccb12e43557e0/logo-hover.png","ACL":[],"is_dir":false,"_version":1,"title":"logo-hover.png","publish_details":[{"environment":"blta23b7a042566724f","locale":"en-us","time":"2020-10-23T07:53:18.776Z","user":"blt624de4139bf66f89","version":1}]},"link":{"title":"Logo","href":"/"}},"navigation_section":{"navigation_bar":[{"title":"Home","_metadata":{"uid":"cs38f8006bc6beaa51"},"link":"/"},{"title":"Blog","_metadata":{"uid":"cs15fd532f732f3825"},"link":"#"}]},"cta":{"title":"","link":"","open_new_tab":false},"tags":[],"locale":"en-us","ACL":{},"uid":"blte7e24e3f9396bf50","_version":1,"_in_progress":false,"publish_details":[{"environment":"blta23b7a042566724f","locale":"en-us","time":"2020-10-23T07:53:41.130Z","user":"blt624de4139bf66f89","version":1}]}}