{"blt74c3b1e671adfceb":{"title":"Header","url":"#","logo":{"image":{"uid":"bltdc9292a4f1c2ba9c","created_at":"2020-09-23T09:32:33.934Z","updated_at":"2020-09-23T09:32:33.934Z","created_by":"blt178d1e9ead4fa070","updated_by":"blt178d1e9ead4fa070","content_type":"image/png","file_size":"1860","tags":[],"filename":"logo-hover.png","url":"https://images.contentstack.io/v3/assets/blt45238cc3dfab42d3/bltdc9292a4f1c2ba9c/5f6b16318350724defa21cbb/logo-hover.png","ACL":[],"is_dir":false,"_version":1,"title":"logo-hover.png","publish_details":[{"environment":"bltb36b8e7960f65071","locale":"en-us","time":"2020-09-23T10:13:52.340Z","user":"blt178d1e9ead4fa070","version":1}]},"link":{"title":"","href":""}},"navigation_section":{"navigation_bar":[{"title":"Home","link":"/"},{"title":"Blog","link":"#"}]},"cta":{"title":"","link":"","open_new_tab":false},"tags":[],"locale":"en-us","uid":"blt74c3b1e671adfceb","ACL":{},"_version":3,"_in_progress":false,"publish_details":[{"environment":"bltb36b8e7960f65071","locale":"en-us","time":"2020-09-23T10:13:52.340Z","user":"blt178d1e9ead4fa070","version":3}]}}