{"blta66060dcdb674d7d":{"title":"Home page","url":"/","hero_banner_section":{"image":{"uid":"blt1d31ad10cd9d53df","created_at":"2020-08-11T15:11:45.406Z","updated_at":"2020-08-11T15:11:45.406Z","created_by":"blt828ab71437a69a50","updated_by":"blt828ab71437a69a50","content_type":"image/jpeg","file_size":"100780","tags":[],"filename":"photo-1484807352052-23338990c6c6.jpeg","url":"https://stag-images.contentstack.io/v3/assets/blt9409ecd3f01de6c2/blt1d31ad10cd9d53df/5f32b531514e7f103f2db587/photo-1484807352052-23338990c6c6.jpeg","ACL":[],"is_dir":false,"parent_uid":null,"_version":1,"title":"photo-1484807352052-23338990c6c6.jpeg","publish_details":[{"environment":"blt38a40709bf8d00ee","locale":"en-us","time":"2020-08-11T15:12:21.747Z","user":"blt828ab71437a69a50","version":1}]},"heading":"Welcome To Home Page","description":"Content and influence over the customers are the most powerful things on the internet. Content creation and distribution creates an iconic digital experience. However, if this experience is poor, it may result in becoming an obstacle to your customers'digital journey. It is therefore critical for every business to manage and deliver quality content to remain competitive.","cta":{"title":"#","href":"#"}},"about_section":{"heading":"Heading","description":"Content and influence over the customers are the most powerful things on the internet. Content creation and distribution creates an iconic digital experience. However, if this experience is poor, it may result in becoming an obstacle to your customers'digital journey. It is therefore critical for every business to manage and deliver quality content to remain competitive."},"group":{"heading":"Testimonials","testimonial_detail":[{"image":{"uid":"blt8dd4cb3a64000088","created_at":"2020-07-21T11:35:56.982Z","updated_at":"2020-07-21T11:35:56.982Z","created_by":"blt828ab71437a69a50","updated_by":"blt828ab71437a69a50","content_type":"image/jpeg","file_size":"270634","tags":[],"filename":"variation_one.jpeg","url":"https://stag-images.contentstack.io/v3/assets/blt9409ecd3f01de6c2/blt8dd4cb3a64000088/5f16d31c1cc44e0f7c87380c/variation_one.jpeg","ACL":[],"is_dir":false,"parent_uid":null,"_version":1,"title":"variation_one.jpeg","publish_details":[{"environment":"blt38a40709bf8d00ee","locale":"en-us","time":"2020-07-23T13:03:39.834Z","user":"blt828ab71437a69a50","version":1}]},"heading":"Testimonials 1","description":"<p>Their product allows our content managers to focus on their content while the UX Team focuses on creating a favorable flow for all website visitors.</p>","_metadata":{"uid":"cse5f089ff9e3796ac"}},{"image":{"uid":"blt68e389edbd4fd720","created_at":"2020-07-31T13:05:43.736Z","updated_at":"2020-07-31T13:05:43.736Z","created_by":"blt828ab71437a69a50","updated_by":"blt828ab71437a69a50","content_type":"image/png","file_size":"331966","tags":[],"filename":"product-bg.png","url":"https://stag-images.contentstack.io/v3/assets/blt9409ecd3f01de6c2/blt68e389edbd4fd720/5f241727b4c26a0f99ac94ff/product-bg.png","ACL":[],"is_dir":false,"parent_uid":null,"_version":1,"title":"product-bg.png","publish_details":[{"environment":"blt38a40709bf8d00ee","locale":"en-us","time":"2020-07-31T13:05:56.620Z","user":"blt828ab71437a69a50","version":1}]},"heading":"Testimonial 2","description":"<p>Their product allows our content managers to focus on their content while the UX Team focuses on creating a favorable flow for all website visitors.</p>","_metadata":{"uid":"cs780e6fee853c8ee0"}},{"image":{"uid":"blt68e389edbd4fd720","created_at":"2020-07-31T13:05:43.736Z","updated_at":"2020-07-31T13:05:43.736Z","created_by":"blt828ab71437a69a50","updated_by":"blt828ab71437a69a50","content_type":"image/png","file_size":"331966","tags":[],"filename":"product-bg.png","url":"https://stag-images.contentstack.io/v3/assets/blt9409ecd3f01de6c2/blt68e389edbd4fd720/5f241727b4c26a0f99ac94ff/product-bg.png","ACL":[],"is_dir":false,"parent_uid":null,"_version":1,"title":"product-bg.png","publish_details":[{"environment":"blt38a40709bf8d00ee","locale":"en-us","time":"2020-07-31T13:05:56.620Z","user":"blt828ab71437a69a50","version":1}]},"heading":"Testimonial 3","description":"<p>Their product allows our content managers to focus on their content while the UX Team focuses on creating a favorable flow for all website visitors.</p>","_metadata":{"uid":"csf59cf8788bf6bb7c"}}]},"tags":[],"locale":"en-us","uid":"blta66060dcdb674d7d","created_by":"blt828ab71437a69a50","updated_by":"blt828ab71437a69a50","created_at":"2020-08-10T13:38:55.082Z","updated_at":"2020-08-11T15:11:55.797Z","_version":6,"_in_progress":false,"publish_details":[{"environment":"blt38a40709bf8d00ee","locale":"en-us","time":"2020-08-11T15:12:21.747Z","user":"blt828ab71437a69a50","version":6}]}}