[{"stackHeaders":{"api_key":"blt3b695b375889bf27","authorization":"cs2fa07d095f1ca3d48fcdda98"},"urlPath":"/assets/blt006830424a708996","uid":"blt006830424a708996","content_type":"image/png","file_size":"1860","tags":[],"filename":"logo-hover.png","url":"https://images.contentstack.io/v3/assets/blt3b695b375889bf27/blt006830424a708996/5f92bea80e0c6d2c075eab82/logo-hover.png","ACL":{},"is_dir":false,"parent_uid":null,"_version":1,"title":"logo-hover.png","publish_details":[{"environment":"blt246e7fdbbe7096e0","locale":"en-us","time":"2020-10-23T11:29:46.899Z","user":"blt7b4c2af5a5618ddc","version":1}]}]